mnemopy/__init__.py
mnemopy/layout-main_window.py
mnemopy/main.py
mnemopy/mnemopy.py
mnemopy/resources.py
mnemopy-0.1.dist-info/LICENSE
mnemopy-0.1.dist-info/METADATA
mnemopy-0.1.dist-info/WHEEL
mnemopy-0.1.dist-info/entry_points.txt
mnemopy-0.1.dist-info/top_level.txt
mnemopy-0.1.dist-info/RECORD
